{"best_agent": {"identity": "~/.ssh/id_rsa/", "agent_path": "best_agent_123", "agent_configuration": "company:\n  name: Tech Innovators Inc.\n  location:\n    address: 123 Technology Way\n    city: Innovation City\n    state: CA\n    zip: \"94000\"\n  departments:\n    - name: Research and Development\n      employees:\n        - id: 1\n          name: Alice Johnson\n          position: Lead Engineer\n          skills:\n            - C++\n            - Python\n            - Machine Learning\n        - id: 2\n          name: Bob Smith\n          position: Data Scientist\n          skills:\n            - Python\n            - R\n            - Statistics\n    - name: Marketing\n      employees:\n        - id: 3\n          name: Carol Williams\n          position: Marketing Manager\n          skills:\n            - SEO\n            - Content Marketing\n            - Social Media\n        - id: 4\n          name: David Brown\n          position: Digital Strategist\n          skills:\n            - Analytics\n            - PPC\n            - Copywriting\n  products:\n    - id: 101\n      name: Product Alpha\n      category: Software\n      price: 299.99\n      features:\n        - Cloud-based\n        - User-friendly\n        - Secure\n    - id: 102\n      name: Gadget Beta\n      category: Hardware\n      price: 149.99\n      features:\n        - Portable\n        - High-speed\n        - Energy-efficient\nlatestUpdate: \"2023-10-01T12:00:00Z\"", "config_store_entries": {"what": {"type": "JSON", "content": {"dude...": {"name": "Tech Innovators Inc.", "location": {"address": "123 Technology Way", "city": "Innovation City", "state": "CA", "zip": "94000"}, "departments": [{"name": "Research and Development", "employees": [{"id": 1, "name": "Alice Johnson", "position": "Lead Engineer", "skills": ["C++", "Python", "Machine Learning"]}, {"id": 2, "name": "Bob Smith", "position": "Data Scientist", "skills": ["Python", "R", "Statistics"]}]}, {"name": "Marketing", "employees": [{"id": 3, "name": "Carol Williams", "position": "Marketing Manager", "skills": ["SEO", "Content Marketing", "Social Media"]}, {"id": 4, "name": "David Brown", "position": "Digital Strategist", "skills": ["Analytics", "PPC", "Copywriting"]}]}], "products": [{"id": 101, "name": "Product Alpha", "category": "Software", "price": 299.99, "features": ["Cloud-based", "User-friendly", "Secure"]}, {"id": 102, "name": "Gadget Beta", "category": "Hardware", "price": 149.99, "features": ["Portable", "High-speed", "Energy-efficient"]}]}, "latestUpdate": "2023-10-01T12:00:00Z"}}}}, "8989": {"identity": "~/.ssh/id_rsa/", "agent_path": "me", "agent_configuration": {"user": {"id": 12345, "name": "John Doe", "email": "john.doe@example.com", "age": 30, "gender": "male", "is_active": true, "preferences": {"newsletter": true, "notifications": {"email": true, "sms": false}}, "address": {"street": "123 Main St", "city": "Anytown", "state": "Anystate", "zipcode": "12345"}, "last_login": "2023-10-01T12:34:56Z"}}, "config_store_entries": {}}}